krypt/__init__.py
krypt/__main__.py
krypt/main.py
krypt/parser.py
krypt/actions/__init__.py
krypt/actions/init.py
krypt/actions/seal.py
krypt/actions/unseal.py
krypt/actions/argument_parsers/__init__.py
krypt/actions/argument_parsers/init.py
krypt/actions/argument_parsers/seal.py
krypt/actions/argument_parsers/unseal.py
krypt/actions/preflight_checks/__init__.py
krypt/actions/preflight_checks/init.py
krypt/actions/preflight_checks/seal.py
krypt/actions/preflight_checks/unseal.py
krypt/pki/__init__.py
krypt/pki/decryptor.py
krypt/pki/encryptor.py
krypt/pki/keypair.py
krypt/util/__init__.py
krypt/util/git_util.py
krypt/util/meta_util.py
krypt/util/path_util.py
krypt/util/zip_util.py
krypt-0.1.2.dist-info/METADATA
krypt-0.1.2.dist-info/WHEEL
krypt-0.1.2.dist-info/entry_points.txt
krypt-0.1.2.dist-info/licenses/LICENSE
krypt-0.1.2.dist-info/RECORD
