Metadata-Version: 2.3
Name: krypt
Version: 0.1.2
Summary: A helper tool for file encryption in Git repositories primarily aimed at encrypting Kubernetes secrets and other sensitive information to be later used in a CI/CD pipeline
Project-URL: Homepage, https://github.com/kubertools/krypt
Project-URL: Issues, https://github.com/kubertools/krypt/issues
Author-email: Kubermate <168834048+kubermate@users.noreply.github.com>
License-File: LICENSE
Keywords: ci/cd pipeline,encryption,gitops,kubernetes,secrets
Classifier: Development Status :: 4 - Beta
Classifier: Environment :: Console
Classifier: License :: OSI Approved :: GNU General Public License v3 (GPLv3)
Classifier: Operating System :: OS Independent
Classifier: Programming Language :: Python :: 3
Classifier: Topic :: Utilities
Requires-Python: >=3.8
Requires-Dist: cffi>=1.16.0
Requires-Dist: cryptography>=42.0.5
Requires-Dist: pycparser>=2.22
